ccl_leveldbase.py
ccl_leveldbase-1.2.dist-info/LICENSE
ccl_leveldbase-1.2.dist-info/METADATA
ccl_leveldbase-1.2.dist-info/WHEEL
ccl_leveldbase-1.2.dist-info/RECORD
